AWSIoTDeviceDefenderAgentSDK/__init__.py
AWSIoTDeviceDefenderAgentSDK/agent.py
AWSIoTDeviceDefenderAgentSDK/collector.py
AWSIoTDeviceDefenderAgentSDK/metrics.py
AWSIoTDeviceDefenderAgentSDK/tags.py
AWSIoTDeviceDefenderAgentSDK-2.0.0.dist-info/DESCRIPTION.rst
AWSIoTDeviceDefenderAgentSDK-2.0.0.dist-info/METADATA
AWSIoTDeviceDefenderAgentSDK-2.0.0.dist-info/RECORD
AWSIoTDeviceDefenderAgentSDK-2.0.0.dist-info/WHEEL
AWSIoTDeviceDefenderAgentSDK-2.0.0.dist-info/metadata.json
AWSIoTDeviceDefenderAgentSDK-2.0.0.dist-info/top_level.txt
