Metadata-Version: 2.0
Name: AWSIoTDeviceDefenderAgentSDK
Version: 2.0.0
Summary: AWS IoT Device Defender Agent SDK
Home-page: https://github.com/aws-samples/aws-iot-device-defender-agent-sdk-python
Author: Amazon Web Services
Author-email: aws-iot-device-defender@amazon.com
License: APACHE.20
Platform: UNKNOWN
Classifier: Development Status :: 5 - Production/Stable
Classifier: Intended Audience :: Developers
Classifier: Natural Language :: English
Classifier: License :: OSI Approved :: Apache Software License
Classifier: Programming Language :: Python
Classifier: Programming Language :: Python :: 3.5
Classifier: Programming Language :: Python :: 3.6
Classifier: Programming Language :: Python :: 3.7
Requires-Dist: psutil
Requires-Dist: cbor
Requires-Dist: awsiotsdk
